README.md
setup.cfg
setup.py
command_groups/__init__.py
command_groups/deployments.py
command_groups/projects.py
tbs_cli.egg-info/PKG-INFO
tbs_cli.egg-info/SOURCES.txt
tbs_cli.egg-info/dependency_links.txt
tbs_cli.egg-info/entry_points.txt
tbs_cli.egg-info/requires.txt
tbs_cli.egg-info/top_level.txt
tbscli/CONSTANTS.py
tbscli/__init__.py
tbscli/decorators.py
tbscli/tbs.py