Metadata-Version: 1.1
Name: tbs-cli
Version: 0.1.0
Summary: 3Blades Command Line Tool
Home-page: https://github.com/3Blades/python-cli-tools
Author: John Griebel
Author-email: jgriebel@3blades.io
License: BSD 3-clause
Download-URL: https://github.com/3Blades/python-cli-tools/archive/0.1.0.tar.gz
Keywords: 3Blades,Data Science
Platform: UNKNOWN
